plugllm/__init__.py
plugllm/chat.py
plugllm/config.py
plugllm/core.py
plugllm/prompts.py
plugllm/providers/__init__.py
plugllm/providers/base.py
plugllm/providers/gemini.py
plugllm/providers/groq.py
plugllm/providers/mistral.py
plugllm/providers/openai.py
plugllm-0.1.2.dist-info/licenses/LICENSE
plugllm-0.1.2.dist-info/METADATA
plugllm-0.1.2.dist-info/WHEEL
plugllm-0.1.2.dist-info/top_level.txt
plugllm-0.1.2.dist-info/RECORD
