Metadata-Version: 2.4
Name: plugllm
Version: 0.1.2
Summary: Unified LLM API interface for OpenAI, Gemini, Mistral, Groq and more.
Home-page: https://github.com/firoziya/plugllm
Author: Yash Kumar Firoziya
Author-email: ykfiroziya@gmail.com
License: MIT
Project-URL: Documentation, https://github.com/firoziya/plugllm#readme
Project-URL: Source Code, https://github.com/firoziya/plugllm
Keywords: llm api openai gemini mistral groq ai chatbot
Classifier: Development Status :: 4 - Beta
Classifier: Intended Audience :: Developers
Classifier: License :: OSI Approved :: MIT License
Classifier: Programming Language :: Python :: 3
Classifier: Programming Language :: Python :: 3.7
Classifier: Programming Language :: Python :: 3.8
Classifier: Programming Language :: Python :: 3.9
Classifier: Programming Language :: Python :: 3.10
Classifier: Programming Language :: Python :: 3.11
Classifier: Topic :: Software Development :: Libraries
Requires-Python: >=3.7
License-File: LICENSE
Requires-Dist: requests>=2.20.0
Dynamic: author
Dynamic: author-email
Dynamic: classifier
Dynamic: description
Dynamic: description-content-type
Dynamic: home-page
Dynamic: keywords
Dynamic: license
Dynamic: license-file
Dynamic: project-url
Dynamic: requires-dist
Dynamic: requires-python
Dynamic: summary
